trax/__init__.py
trax/import_test.py
trax/jaxboard.py
trax/predict_drop.py
trax/rl_trainer.py
trax/shapes.py
trax/shapes_test.py
trax/test_utils.py
trax/trainer.py
trax/trainer_flags.py
trax/trax2keras.py
trax/trax2keras_test.py
trax/data/__init__.py
trax/data/debug_data_pipeline.py
trax/data/inputs.py
trax/data/inputs_test.py
trax/data/text_encoder.py
trax/data/text_encoder_build_subword.py
trax/data/text_encoder_test.py
trax/data/tf_inputs.py
trax/data/tf_inputs_test.py
trax/data/tokenizer.py
trax/data/tokenizer_test.py
trax/fastmath/__init__.py
trax/fastmath/jax.py
trax/fastmath/numpy.py
trax/fastmath/ops.py
trax/fastmath/ops_test.py
trax/fastmath/tf.py
trax/layers/__init__.py
trax/layers/acceleration.py
trax/layers/acceleration_test.py
trax/layers/activation_fns.py
trax/layers/activation_fns_test.py
trax/layers/assert_shape.py
trax/layers/assert_shape_test.py
trax/layers/attention.py
trax/layers/attention_test.py
trax/layers/base.py
trax/layers/base_test.py
trax/layers/combinators.py
trax/layers/combinators_test.py
trax/layers/convolution.py
trax/layers/convolution_test.py
trax/layers/core.py
trax/layers/core_test.py
trax/layers/deconvolution.py
trax/layers/deconvolution_test.py
trax/layers/initializers.py
trax/layers/initializers_test.py
trax/layers/metrics.py
trax/layers/metrics_test.py
trax/layers/normalization.py
trax/layers/normalization_test.py
trax/layers/pooling.py
trax/layers/pooling_test.py
trax/layers/reversible.py
trax/layers/reversible_test.py
trax/layers/rnn.py
trax/layers/rnn_test.py
trax/layers/test_utils.py
trax/layers/test_utils_test.py
trax/layers/research/__init__.py
trax/layers/research/efficient_attention.py
trax/layers/research/efficient_attention_test.py
trax/layers/research/position_encodings.py
trax/layers/research/position_encodings_test.py
trax/layers/research/rel_attention.py
trax/layers/research/rel_attention_test.py
trax/layers/research/resampling.py
trax/layers/research/rotary_positional_embedding.py
trax-1.4.1.dist-info/AUTHORS
trax-1.4.1.dist-info/LICENSE
trax-1.4.1.dist-info/METADATA
trax-1.4.1.dist-info/WHEEL
trax-1.4.1.dist-info/top_level.txt
trax-1.4.1.dist-info/RECORD
